flake8_sarif_reporter/__init__.py
flake8_sarif_reporter/reporters.py
flake8_sarif_reporter/sarifdata.py
flake8_sarif-1.0.15.dist-info/LICENSE
flake8_sarif-1.0.15.dist-info/METADATA
flake8_sarif-1.0.15.dist-info/WHEEL
flake8_sarif-1.0.15.dist-info/entry_points.txt
flake8_sarif-1.0.15.dist-info/top_level.txt
flake8_sarif-1.0.15.dist-info/RECORD
